{"v":"4.8.0","meta":{"g":"LottieFiles AE 3.4.5","a":"","k":"","d":"","tc":""},"fr":30,"ip":0,"op":50,"w":512,"h":512,"nm":"Versus","ddd":0,"assets":[{"id":"comp_0","layers":[{"ddd":0,"ind":1,"ty":0,"nm":"dots","refId":"comp_1","sr":1,"ks":{"o":{"a":0,"k":100,"ix":11},"r":{"a":0,"k":0,"ix":10},"p":{"a":0,"k":[400,300,0],"ix":2},"a":{"a":0,"k":[200,200,0],"ix":1},"s":{"a":0,"k":[100,100,100],"ix":6}},"ao":0,"w":400,"h":400,"ip":0,"op":191.191191191191,"st":0,"bm":0}]},{"id":"comp_1","layers":[{"ddd":0,"ind":1,"ty":4,"nm":"Слой 10 Outlines","sr":1,"ks":{"o":{"a":0,"k":100,"ix":11},"r":{"a":0,"k":0,"ix":10},"p":{"a":1,"k":[{"i":{"x":0.667,"y":1},"o":{"x":0.333,"y":0},"t":0,"s":[243,61.5,0],"to":[0,0,0],"ti":[0,0,0]},{"i":{"x":0.667,"y":1},"o":{"x":0.333,"y":0},"t":24.024,"s":[225,88.5,0],"to":[0,0,0],"ti":[0,0,0]},{"i":{"x":0.667,"y":1},"o":{"x":0.333,"y":0},"t":47.047,"s":[243,61.5,0],"to":[0,0,0],"ti":[0,0,0]},{"i":{"x":0.667,"y":1},"o":{"x":0.333,"y":0},"t":94.094,"s":[227,84.5,0],"to":[0,0,0],"ti":[0,0,0]},{"i":{"x":0.667,"y":1},"o":{"x":0.333,"y":0},"t":121.121,"s":[243,61.5,0],"to":[0,0,0],"ti":[0,0,0]},{"i":{"x":0.667,"y":1},"o":{"x":0.333,"y":0},"t":168.168,"s":[218,96.5,0],"to":[0,0,0],"ti":[0,0,0]},{"t":189.189189189189,"s":[243,61.5,0]}],"ix":2},"a":{"a":0,"k":[3.75,3.75,0],"ix":1},"s":{"a":0,"k":[132,132,100],"ix":6}},"ao":0,"shapes":[{"ty":"gr","it":[{"ind":0,"ty":"sh","ix":1,"ks":{"a":0,"k":{"i":[[1.933,0],[0,-1.933],[-1.933,0],[0,1.933]],"o":[[-1.933,0],[0,1.933],[1.933,0],[0,-1.933]],"v":[[0,-3.5],[-3.5,0],[0,3.5],[3.5,0]],"c":true},"ix":2},"nm":"Path 1","mn":"ADBE Vector Shape - Group","hd":false},{"ty":"fl","c":{"a":0,"k":[0.101960784314,0.529411764706,1,1],"ix":4},"o":{"a":0,"k":100,"ix":5},"r":1,"bm":0,"nm":"Fill 1","mn":"ADBE Vector Graphic - Fill","hd":false},{"ty":"tr","p":{"a":0,"k":[3.75,3.75],"ix":2},"a":{"a":0,"k":[0,0],"ix":1},"s":{"a":0,"k":[100,100],"ix":3},"r":{"a":0,"k":0,"ix":6},"o":{"a":0,"k":100,"ix":7},"sk":{"a":0,"k":0,"ix":4},"sa":{"a":0,"k":0,"ix":5},"nm":"Transform"}],"nm":"Group 1","np":2,"cix":2,"bm":0,"ix":1,"mn":"ADBE Vector Group","hd":false}],"ip":0,"op":191.191191191191,"st":0,"bm":0},{"ddd":0,"ind":2,"ty":4,"nm":"Слой 9 Outlines","sr":1,"ks":{"o":{"a":0,"k":100,"ix":11},"r":{"a":0,"k":0,"ix":10},"p":{"a":1,"k":[{"i":{"x":0.667,"y":1},"o":{"x":0.333,"y":0},"t":0,"s":[277,188.5,0],"to":[0,0,0],"ti":[0,0,0]},{"i":{"x":0.667,"y":1},"o":{"x":0.333,"y":0},"t":39.039,"s":[251,173.5,0],"to":[0,0,0],"ti":[0,0,0]},{"i":{"x":0.667,"y":1},"o":{"x":0.333,"y":0},"t":91.091,"s":[277,188.5,0],"to":[0,0,0],"ti":[0,0,0]},{"i":{"x":0.667,"y":1},"o":{"x":0.333,"y":0},"t":146.146,"s":[259,177.5,0],"to":[0,0,0],"ti":[0,0,0]},{"t":190.19019019019,"s":[277,188.5,0]}],"ix":2},"a":{"a":0,"k":[7.75,7.75,0],"ix":1},"s":{"a":0,"k":[132,132,100],"ix":6}},"ao":0,"shapes":[{"ty":"gr","it":[{"ind":0,"ty":"sh","ix":1,"ks":{"a":0,"k":{"i":[[4.143,0],[0,-4.142],[-4.143,0],[0,4.142]],"o":[[-4.143,0],[0,4.142],[4.143,0],[0,-4.142]],"v":[[0,-7.5],[-7.5,0],[0,7.5],[7.5,0]],"c":true},"ix":2},"nm":"Path 1","mn":"ADBE Vector Shape - Group","hd":false},{"ty":"fl","c":{"a":0,"k":[0.101960784314,0.529411764706,1,1],"ix":4},"o":{"a":0,"k":100,"ix":5},"r":1,"bm":0,"nm":"Fill 1","mn":"ADBE Vector Graphic - Fill","hd":false},{"ty":"tr","p":{"a":0,"k":[7.75,7.75],"ix":2},"a":{"a":0,"k":[0,0],"ix":1},"s":{"a":0,"k":[100,100],"ix":3},"r":{"a":0,"k":0,"ix":6},"o":{"a":0,"k":100,"ix":7},"sk":{"a":0,"k":0,"ix":4},"sa":{"a":0,"k":0,"ix":5},"nm":"Transform"}],"nm":"Group 1","np":2,"cix":2,"bm":0,"ix":1,"mn":"ADBE Vector Group","hd":false}],"ip":0,"op":191.191191191191,"st":0,"bm":0},{"ddd":0,"ind":3,"ty":4,"nm":"Слой 8 Outlines","sr":1,"ks":{"o":{"a":0,"k":100,"ix":11},"r":{"a":0,"k":0,"ix":10},"p":{"a":1,"k":[{"i":{"x":0.667,"y":1},"o":{"x":0.333,"y":0},"t":0,"s":[301,120.5,0],"to":[0,0,0],"ti":[0,0,0]},{"i":{"x":0.667,"y":1},"o":{"x":0.333,"y":0},"t":15.015,"s":[277,137.5,0],"to":[0,0,0],"ti":[0,0,0]},{"i":{"x":0.667,"y":1},"o":{"x":0.333,"y":0},"t":38.038,"s":[301,120.5,0],"to":[0,0,0],"ti":[0,0,0]},{"i":{"x":0.667,"y":1},"o":{"x":0.333,"y":0},"t":64.064,"s":[276,139.5,0],"to":[0,0,0],"ti":[0,0,0]},{"i":{"x":0.667,"y":1},"o":{"x":0.333,"y":0},"t":105.105,"s":[301,120.5,0],"to":[0,0,0],"ti":[0,0,0]},{"i":{"x":0.667,"y":1},"o":{"x":0.333,"y":0},"t":156.156,"s":[287,129.5,0],"to":[0,0,0],"ti":[0,0,0]},{"t":189.189189189189,"s":[301,120.5,0]}],"ix":2},"a":{"a":0,"k":[11.75,11.75,0],"ix":1},"s":{"a":0,"k":[132,132,100],"ix":6}},"ao":0,"shapes":[{"ty":"gr","it":[{"ind":0,"ty":"sh","ix":1,"ks":{"a":0,"k":{"i":[[6.352,0],[0,-6.351],[-6.352,0],[0,6.351]],"o":[[-6.352,0],[0,6.351],[6.352,0],[0,-6.351]],"v":[[0,-11.5],[-11.5,0],[0,11.5],[11.5,0]],"c":true},"ix":2},"nm":"Path 1","mn":"ADBE Vector Shape - Group","hd":false},{"ty":"fl","c":{"a":0,"k":[0.980392156863,0.207843137255,0.458823529412,1],"ix":4},"o":{"a":0,"k":100,"ix":5},"r":1,"bm":0,"nm":"Fill 1","mn":"ADBE Vector Graphic - Fill","hd":false},{"ty":"tr","p":{"a":0,"k":[11.75,11.75],"ix":2},"a":{"a":0,"k":[0,0],"ix":1},"s":{"a":0,"k":[100,100],"ix":3},"r":{"a":0,"k":0,"ix":6},"o":{"a":0,"k":100,"ix":7},"sk":{"a":0,"k":0,"ix":4},"sa":{"a":0,"k":0,"ix":5},"nm":"Transform"}],"nm":"Group 1","np":2,"cix":2,"bm":0,"ix":1,"mn":"ADBE Vector Group","hd":false}],"ip":0,"op":191.191191191191,"st":0,"bm":0},{"ddd":0,"ind":4,"ty":4,"nm":"Слой 7 Outlines","sr":1,"ks":{"o":{"a":0,"k":100,"ix":11},"r":{"a":0,"k":0,"ix":10},"p":{"a":1,"k":[{"i":{"x":0.667,"y":1},"o":{"x":0.333,"y":0},"t":0,"s":[153,330.5,0],"to":[0,0,0],"ti":[0,0,0]},{"i":{"x":0.667,"y":1},"o":{"x":0.333,"y":0},"t":19.019,"s":[169,289.5,0],"to":[0,0,0],"ti":[0,0,0]},{"i":{"x":0.667,"y":1},"o":{"x":0.333,"y":0},"t":51.051,"s":[153,330.5,0],"to":[0,0,0],"ti":[0,0,0]},{"i":{"x":0.667,"y":1},"o":{"x":0.333,"y":0},"t":85.085,"s":[176,272.5,0],"to":[0,0,0],"ti":[0,0,0]},{"i":{"x":0.667,"y":1},"o":{"x":0.333,"y":0},"t":116.116,"s":[153,330.5,0],"to":[0,0,0],"ti":[0,0,0]},{"i":{"x":0.667,"y":1},"o":{"x":0.333,"y":0},"t":156.156,"s":[164,297.5,0],"to":[0,0,0],"ti":[0,0,0]},{"t":189.189189189189,"s":[153,330.5,0]}],"ix":2},"a":{"a":0,"k":[11.75,11.75,0],"ix":1},"s":{"a":0,"k":[132,132,100],"ix":6}},"ao":0,"shapes":[{"ty":"gr","it":[{"ind":0,"ty":"sh","ix":1,"ks":{"a":0,"k":{"i":[[-6.351,0],[0,-6.352],[6.351,0],[0,6.352]],"o":[[6.351,0],[0,6.352],[-6.351,0],[0,-6.352]],"v":[[0,-11.5],[11.5,0],[0,11.5],[-11.5,0]],"c":true},"ix":2},"nm":"Path 1","mn":"ADBE Vector Shape - Group","hd":false},{"ty":"fl","c":{"a":0,"k":[0.101960784314,0.529411764706,1,1],"ix":4},"o":{"a":0,"k":100,"ix":5},"r":1,"bm":0,"nm":"Fill 1","mn":"ADBE Vector Graphic - Fill","hd":false},{"ty":"tr","p":{"a":0,"k":[11.75,11.75],"ix":2},"a":{"a":0,"k":[0,0],"ix":1},"s":{"a":0,"k":[100,100],"ix":3},"r":{"a":0,"k":0,"ix":6},"o":{"a":0,"k":100,"ix":7},"sk":{"a":0,"k":0,"ix":4},"sa":{"a":0,"k":0,"ix":5},"nm":"Transform"}],"nm":"Group 1","np":2,"cix":2,"bm":0,"ix":1,"mn":"ADBE Vector Group","hd":false}],"ip":0,"op":191.191191191191,"st":0,"bm":0},{"ddd":0,"ind":5,"ty":4,"nm":"Слой 6 Outlines","sr":1,"ks":{"o":{"a":0,"k":100,"ix":11},"r":{"a":0,"k":0,"ix":10},"p":{"a":1,"k":[{"i":{"x":0.667,"y":1},"o":{"x":0.333,"y":0},"t":0,"s":[80,280.5,0],"to":[0,0,0],"ti":[0,0,0]},{"i":{"x":0.667,"y":1},"o":{"x":0.333,"y":0},"t":28.028,"s":[122,237.5,0],"to":[0,0,0],"ti":[0,0,0]},{"i":{"x":0.667,"y":1},"o":{"x":0.333,"y":0},"t":57.057,"s":[80,280.5,0],"to":[0,0,0],"ti":[0,0,0]},{"i":{"x":0.667,"y":1},"o":{"x":0.333,"y":0},"t":77.077,"s":[108,253.5,0],"to":[0,0,0],"ti":[0,0,0]},{"i":{"x":0.667,"y":1},"o":{"x":0.333,"y":0},"t":104.104,"s":[80,280.5,0],"to":[0,0,0],"ti":[0,0,0]},{"i":{"x":0.667,"y":1},"o":{"x":0.333,"y":0},"t":132.132,"s":[101,261.5,0],"to":[0,0,0],"ti":[0,0,0]},{"i":{"x":0.667,"y":1},"o":{"x":0.333,"y":0},"t":143.143,"s":[80,280.5,0],"to":[0,0,0],"ti":[0,0,0]},{"i":{"x":0.667,"y":1},"o":{"x":0.333,"y":0},"t":170.17,"s":[111,252.5,0],"to":[0,0,0],"ti":[0,0,0]},{"t":189.189189189189,"s":[80,280.5,0]}],"ix":2},"a":{"a":0,"k":[5.75,5.75,0],"ix":1},"s":{"a":0,"k":[132,132,100],"ix":6}},"ao":0,"shapes":[{"ty":"gr","it":[{"ind":0,"ty":"sh","ix":1,"ks":{"a":0,"k":{"i":[[3.038,0],[0,-3.037],[-3.038,0],[0,3.037]],"o":[[-3.038,0],[0,3.037],[3.038,0],[0,-3.037]],"v":[[0,-5.5],[-5.5,0],[0,5.5],[5.5,0]],"c":true},"ix":2},"nm":"Path 1","mn":"ADBE Vector Shape - Group","hd":false},{"ty":"fl","c":{"a":0,"k":[0.101960784314,0.529411764706,1,1],"ix":4},"o":{"a":0,"k":100,"ix":5},"r":1,"bm":0,"nm":"Fill 1","mn":"ADBE Vector Graphic - Fill","hd":false},{"ty":"tr","p":{"a":0,"k":[5.75,5.75],"ix":2},"a":{"a":0,"k":[0,0],"ix":1},"s":{"a":0,"k":[100,100],"ix":3},"r":{"a":0,"k":0,"ix":6},"o":{"a":0,"k":100,"ix":7},"sk":{"a":0,"k":0,"ix":4},"sa":{"a":0,"k":0,"ix":5},"nm":"Transform"}],"nm":"Group 1","np":2,"cix":2,"bm":0,"ix":1,"mn":"ADBE Vector Group","hd":false}],"ip":0,"op":191.191191191191,"st":0,"bm":0},{"ddd":0,"ind":6,"ty":4,"nm":"Слой 5 Outlines","sr":1,"ks":{"o":{"a":0,"k":100,"ix":11},"r":{"a":0,"k":0,"ix":10},"p":{"a":1,"k":[{"i":{"x":0.667,"y":1},"o":{"x":0.333,"y":0},"t":0,"s":[292,274.5,0],"to":[0,0,0],"ti":[0,0,0]},{"i":{"x":0.667,"y":1},"o":{"x":0.333,"y":0},"t":37.037,"s":[257,255.5,0],"to":[0,0,0],"ti":[0,0,0]},{"i":{"x":0.667,"y":1},"o":{"x":0.333,"y":0},"t":89.089,"s":[292,274.5,0],"to":[0,0,0],"ti":[0,0,0]},{"i":{"x":0.667,"y":1},"o":{"x":0.333,"y":0},"t":134.134,"s":[236,242.5,0],"to":[0,0,0],"ti":[0,0,0]},{"t":189.189189189189,"s":[292,274.5,0]}],"ix":2},"a":{"a":0,"k":[2.75,2.75,0],"ix":1},"s":{"a":0,"k":[132,132,100],"ix":6}},"ao":0,"shapes":[{"ty":"gr","it":[{"ind":0,"ty":"sh","ix":1,"ks":{"a":0,"k":{"i":[[1.381,0],[0,-1.381],[-1.381,0],[0,1.381]],"o":[[-1.381,0],[0,1.381],[1.381,0],[0,-1.381]],"v":[[0,-2.5],[-2.5,0],[0,2.5],[2.5,0]],"c":true},"ix":2},"nm":"Path 1","mn":"ADBE Vector Shape - Group","hd":false},{"ty":"fl","c":{"a":0,"k":[0.980392156863,0.207843137255,0.458823529412,1],"ix":4},"o":{"a":0,"k":100,"ix":5},"r":1,"bm":0,"nm":"Fill 1","mn":"ADBE Vector Graphic - Fill","hd":false},{"ty":"tr","p":{"a":0,"k":[2.75,2.75],"ix":2},"a":{"a":0,"k":[0,0],"ix":1},"s":{"a":0,"k":[100,100],"ix":3},"r":{"a":0,"k":0,"ix":6},"o":{"a":0,"k":100,"ix":7},"sk":{"a":0,"k":0,"ix":4},"sa":{"a":0,"k":0,"ix":5},"nm":"Transform"}],"nm":"Group 1","np":2,"cix":2,"bm":0,"ix":1,"mn":"ADBE Vector Group","hd":false}],"ip":0,"op":191.191191191191,"st":0,"bm":0},{"ddd":0,"ind":7,"ty":4,"nm":"Слой 4 Outlines","sr":1,"ks":{"o":{"a":0,"k":100,"ix":11},"r":{"a":0,"k":0,"ix":10},"p":{"a":1,"k":[{"i":{"x":0.667,"y":1},"o":{"x":0.333,"y":0},"t":0,"s":[321,276.5,0],"to":[0,0,0],"ti":[0,0,0]},{"i":{"x":0.667,"y":1},"o":{"x":0.333,"y":0},"t":16.016,"s":[278,244.5,0],"to":[0,0,0],"ti":[0,0,0]},{"i":{"x":0.667,"y":1},"o":{"x":0.333,"y":0},"t":41.041,"s":[321,276.5,0],"to":[0,0,0],"ti":[0,0,0]},{"i":{"x":0.667,"y":1},"o":{"x":0.333,"y":0},"t":70.07,"s":[291,257.5,0],"to":[0,0,0],"ti":[0,0,0]},{"i":{"x":0.667,"y":1},"o":{"x":0.333,"y":0},"t":94.094,"s":[321,276.5,0],"to":[0,0,0],"ti":[0,0,0]},{"i":{"x":0.667,"y":1},"o":{"x":0.333,"y":0},"t":124.124,"s":[262,232.5,0],"to":[0,0,0],"ti":[0,0,0]},{"i":{"x":0.667,"y":1},"o":{"x":0.333,"y":0},"t":144.144,"s":[321,276.5,0],"to":[0,0,0],"ti":[0,0,0]},{"i":{"x":0.667,"y":1},"o":{"x":0.333,"y":0},"t":165.165,"s":[286,253.5,0],"to":[0,0,0],"ti":[0,0,0]},{"t":190.19019019019,"s":[321,276.5,0]}],"ix":2},"a":{"a":0,"k":[4.75,4.75,0],"ix":1},"s":{"a":0,"k":[132,132,100],"ix":6}},"ao":0,"shapes":[{"ty":"gr","it":[{"ind":0,"ty":"sh","ix":1,"ks":{"a":0,"k":{"i":[[2.485,0],[0,-2.485],[-2.485,0],[0,2.485]],"o":[[-2.485,0],[0,2.485],[2.485,0],[0,-2.485]],"v":[[0,-4.5],[-4.5,0],[0,4.5],[4.5,0]],"c":true},"ix":2},"nm":"Path 1","mn":"ADBE Vector Shape - Group","hd":false},{"ty":"fl","c":{"a":0,"k":[0.980392156863,0.207843137255,0.458823529412,1],"ix":4},"o":{"a":0,"k":100,"ix":5},"r":1,"bm":0,"nm":"Fill 1","mn":"ADBE Vector Graphic - Fill","hd":false},{"ty":"tr","p":{"a":0,"k":[4.75,4.75],"ix":2},"a":{"a":0,"k":[0,0],"ix":1},"s":{"a":0,"k":[100,100],"ix":3},"r":{"a":0,"k":0,"ix":6},"o":{"a":0,"k":100,"ix":7},"sk":{"a":0,"k":0,"ix":4},"sa":{"a":0,"k":0,"ix":5},"nm":"Transform"}],"nm":"Group 1","np":2,"cix":2,"bm":0,"ix":1,"mn":"ADBE Vector Group","hd":false}],"ip":0,"op":191.191191191191,"st":0,"bm":0},{"ddd":0,"ind":8,"ty":4,"nm":"Слой 3 Outlines","sr":1,"ks":{"o":{"a":0,"k":100,"ix":11},"r":{"a":0,"k":0,"ix":10},"p":{"a":1,"k":[{"i":{"x":0.667,"y":1},"o":{"x":0.333,"y":0},"t":0,"s":[89,76.5,0],"to":[0,0,0],"ti":[0,0,0]},{"i":{"x":0.667,"y":1},"o":{"x":0.333,"y":0},"t":39.039,"s":[123,98.5,0],"to":[0,0,0],"ti":[0,0,0]},{"i":{"x":0.667,"y":1},"o":{"x":0.333,"y":0},"t":85.085,"s":[89,76.5,0],"to":[0,0,0],"ti":[0,0,0]},{"i":{"x":0.667,"y":1},"o":{"x":0.333,"y":0},"t":112.112,"s":[143,113.5,0],"to":[0,0,0],"ti":[0,0,0]},{"i":{"x":0.667,"y":1},"o":{"x":0.333,"y":0},"t":141.141,"s":[81.885,73.866,0],"to":[0,0,0],"ti":[0,0,0]},{"i":{"x":0.667,"y":1},"o":{"x":0.333,"y":0},"t":164.164,"s":[130,103.5,0],"to":[0,0,0],"ti":[0,0,0]},{"t":190.19019019019,"s":[89,76.5,0]}],"ix":2},"a":{"a":0,"k":[3.75,3.75,0],"ix":1},"s":{"a":0,"k":[132,132,100],"ix":6}},"ao":0,"shapes":[{"ty":"gr","it":[{"ind":0,"ty":"sh","ix":1,"ks":{"a":0,"k":{"i":[[-1.933,0],[0,-1.933],[1.933,0],[0,1.933]],"o":[[1.933,0],[0,1.933],[-1.933,0],[0,-1.933]],"v":[[0,-3.5],[3.5,0],[0,3.5],[-3.5,0]],"c":true},"ix":2},"nm":"Path 1","mn":"ADBE Vector Shape - Group","hd":false},{"ty":"fl","c":{"a":0,"k":[0.101960784314,0.529411764706,1,1],"ix":4},"o":{"a":0,"k":100,"ix":5},"r":1,"bm":0,"nm":"Fill 1","mn":"ADBE Vector Graphic - Fill","hd":false},{"ty":"tr","p":{"a":0,"k":[3.75,3.75],"ix":2},"a":{"a":0,"k":[0,0],"ix":1},"s":{"a":0,"k":[100,100],"ix":3},"r":{"a":0,"k":0,"ix":6},"o":{"a":0,"k":100,"ix":7},"sk":{"a":0,"k":0,"ix":4},"sa":{"a":0,"k":0,"ix":5},"nm":"Transform"}],"nm":"Group 1","np":2,"cix":2,"bm":0,"ix":1,"mn":"ADBE Vector Group","hd":false}],"ip":0,"op":191.191191191191,"st":0,"bm":0},{"ddd":0,"ind":9,"ty":4,"nm":"Слой 2 Outlines","sr":1,"ks":{"o":{"a":0,"k":100,"ix":11},"r":{"a":0,"k":0,"ix":10},"p":{"a":1,"k":[{"i":{"x":0.667,"y":1},"o":{"x":0.333,"y":0},"t":0,"s":[94,140.5,0],"to":[3.833,1.667,0],"ti":[0,0,0]},{"i":{"x":0.667,"y":1},"o":{"x":0.333,"y":0},"t":16.016,"s":[117,150.5,0],"to":[0,0,0],"ti":[-2.583,-1.25,0]},{"i":{"x":0.667,"y":1},"o":{"x":0.333,"y":0},"t":40.04,"s":[94,140.5,0],"to":[2.583,1.25,0],"ti":[0,0,0]},{"i":{"x":0.667,"y":1},"o":{"x":0.333,"y":0},"t":63.063,"s":[132.5,158,0],"to":[0,0,0],"ti":[3.583,1.583,0]},{"i":{"x":0.667,"y":1},"o":{"x":0.167,"y":0},"t":85.085,"s":[94,140.5,0],"to":[-3.583,-1.583,0],"ti":[1.833,0.833,0]},{"i":{"x":0.667,"y":1},"o":{"x":0.167,"y":0},"t":101.101,"s":[111,148.5,0],"to":[-1.833,-0.833,0],"ti":[1.167,0.5,0]},{"i":{"x":0.667,"y":1},"o":{"x":0.167,"y":0},"t":122.122,"s":[83,135.5,0],"to":[-1.167,-0.5,0],"ti":[-7.25,-3.333,0]},{"i":{"x":0.667,"y":1},"o":{"x":0.167,"y":0},"t":143.143,"s":[104,145.5,0],"to":[7.25,3.333,0],"ti":[1.667,0.833,0]},{"i":{"x":0.667,"y":1},"o":{"x":0.167,"y":0},"t":169.169,"s":[126.5,155.5,0],"to":[-1.667,-0.833,0],"ti":[5.417,2.5,0]},{"t":189.189189189189,"s":[94,140.5,0]}],"ix":2},"a":{"a":0,"k":[8.75,8.75,0],"ix":1},"s":{"a":0,"k":[132,132,100],"ix":6}},"ao":0,"shapes":[{"ty":"gr","it":[{"ind":0,"ty":"sh","ix":1,"ks":{"a":0,"k":{"i":[[4.694,0],[0,-4.694],[-4.694,0],[0,4.694]],"o":[[-4.694,0],[0,4.694],[4.694,0],[0,-4.694]],"v":[[0,-8.5],[-8.5,0],[0,8.5],[8.5,0]],"c":true},"ix":2},"nm":"Path 1","mn":"ADBE Vector Shape - Group","hd":false},{"ty":"fl","c":{"a":0,"k":[0.980392156863,0.207843137255,0.458823529412,1],"ix":4},"o":{"a":0,"k":100,"ix":5},"r":1,"bm":0,"nm":"Fill 1","mn":"ADBE Vector Graphic - Fill","hd":false},{"ty":"tr","p":{"a":0,"k":[8.75,8.75],"ix":2},"a":{"a":0,"k":[0,0],"ix":1},"s":{"a":0,"k":[100,100],"ix":3},"r":{"a":0,"k":0,"ix":6},"o":{"a":0,"k":100,"ix":7},"sk":{"a":0,"k":0,"ix":4},"sa":{"a":0,"k":0,"ix":5},"nm":"Transform"}],"nm":"Group 1","np":2,"cix":2,"bm":0,"ix":1,"mn":"ADBE Vector Group","hd":false}],"ip":0,"op":191.191191191191,"st":0,"bm":0}]}],"layers":[{"ddd":0,"ind":1,"ty":4,"nm":"TEXT__S Outlines","sr":1,"ks":{"o":{"a":1,"k":[{"i":{"x":[0.667],"y":[1]},"o":{"x":[0.333],"y":[0]},"t":5,"s":[0]},{"i":{"x":[0.833],"y":[1]},"o":{"x":[0.333],"y":[0]},"t":10,"s":[100]},{"i":{"x":[0.833],"y":[1]},"o":{"x":[0.167],"y":[0]},"t":40,"s":[100]},{"t":45,"s":[0]}],"ix":11},"r":{"a":0,"k":0,"ix":10},"p":{"a":1,"k":[{"i":{"x":0.667,"y":1},"o":{"x":0.333,"y":0},"t":0,"s":[-18,692,0],"to":[52.5,-63.833,0],"ti":[0,0,0]},{"i":{"x":0.667,"y":1},"o":{"x":1,"y":0},"t":10,"s":[297,309,0],"to":[0,0,0],"ti":[0,0,0]},{"i":{"x":0.667,"y":1},"o":{"x":0.167,"y":0},"t":16.25,"s":[291.5,282.5,0],"to":[0,0,0],"ti":[-1.5,2.167,0]},{"t":40,"s":[300.5,269.5,0]}],"ix":2},"a":{"a":0,"k":[256,256,0],"ix":1},"s":{"a":1,"k":[{"i":{"x":[0.667,0.667,0.667],"y":[1,1,1]},"o":{"x":[1,1,0.333],"y":[0,0,0]},"t":10,"s":[82.031,82.031,100]},{"i":{"x":[0.667,0.667,0.667],"y":[1,1,1]},"o":{"x":[0.167,0.167,0.167],"y":[0,0,0]},"t":16,"s":[56.25,56.25,100]},{"t":22,"s":[56.25,56.25,100]}],"ix":6}},"ao":0,"shapes":[{"ty":"gr","it":[{"ind":0,"ty":"sh","ix":1,"ks":{"a":0,"k":{"i":[[0,0],[0,0],[4.934,0],[0,0],[2.39,-3.538],[0,0],[-5.586,0],[0,0],[13.841,-24.205],[0,0],[14.647,-1.428],[0,0],[0,0],[-3.569,6.517],[0,0],[-5.399,0.249],[0,0],[-2.452,5.028],[0,0],[7.51,-0.186],[0,0],[-14.803,22.282],[0,0],[-5.399,0],[0,0],[2.7,-5.772]],"o":[[0,0],[-2.11,4.469],[0,0],[-4.282,0],[0,0],[-3.103,4.624],[0,0],[27.898,0],[0,0],[-7.292,12.755],[0,0],[0,0],[-7.416,0.714],[0,0],[2.607,-4.748],[0,0],[5.586,-0.217],[0,0],[3.258,-6.734],[0,0],[-26.749,-0.434],[0,0],[2.979,-4.5],[0,0],[6.392,0],[0,0]],"v":[[175.907,-137.784],[152.291,-87.698],[140.747,-80.374],[40.171,-80.374],[29.496,-74.695],[15.842,-54.368],[21.645,-43.508],[89.202,-43.508],[120.731,10.83],[65.09,108.178],[30.117,130.801],[-159.956,148.893],[-166.07,149.482],[-175.1,135.797],[-136.651,65.447],[-123.742,57.409],[20.062,51.606],[33.096,43.072],[43.368,25.322],[34.12,10.986],[-47.868,13.033],[-75.517,-39.505],[-6.781,-142.997],[6.625,-150.197],[168.087,-150.197],[175.969,-137.784]],"c":true},"ix":2},"nm":"Path 1","mn":"ADBE Vector Shape - Group","hd":false},{"ty":"fl","c":{"a":0,"k":[1,1,1,1],"ix":4},"o":{"a":0,"k":100,"ix":5},"r":1,"bm":0,"nm":"Fill 1","mn":"ADBE Vector Graphic - Fill","hd":false},{"ty":"tr","p":{"a":0,"k":[272.26,256.197],"ix":2},"a":{"a":0,"k":[0,0],"ix":1},"s":{"a":0,"k":[100,100],"ix":3},"r":{"a":0,"k":0,"ix":6},"o":{"a":0,"k":100,"ix":7},"sk":{"a":0,"k":0,"ix":4},"sa":{"a":0,"k":0,"ix":5},"nm":"Transform"}],"nm":"Group 1","np":2,"cix":2,"bm":0,"ix":1,"mn":"ADBE Vector Group","hd":false},{"ty":"gr","it":[{"ind":0,"ty":"sh","ix":1,"ks":{"a":0,"k":{"i":[[0,0],[0,0],[-0.435,0.062],[0,0],[-0.497,1.055],[0,0],[-1.211,0.062],[0,0],[-0.528,1.117],[0,0],[2.358,0.093],[0,0],[-1.086,2.172],[0,0],[-0.062,0.249],[0,0],[2.11,0],[0,0],[2.545,-3.289],[0,0],[-0.062,-5.679],[-57.1,0],[-10.396,0.342],[3.538,-4.5],[0,0],[5.958,-0.217],[0,0],[3.165,-5.12],[0,0],[-4.624,-2.141],[-0.093,-0.031]],"o":[[0,0],[0.434,0.155],[0,0],[1.179,-0.093],[0,0],[0.527,-1.117],[0,0],[1.241,-0.062],[0,0],[0.993,-2.141],[0,0],[-2.421,-0.062],[0,0],[0.124,-0.248],[0,0],[0.466,-2.048],[0,0],[-4.128,0],[0,0],[-3.475,4.499],[0.155,19.178],[12.475,0],[5.71,-0.186],[0,0],[-3.662,4.686],[0,0],[-6.02,0.218],[0,0],[-2.669,4.314],[0,0],[0,0]],"v":[[-139.987,138.032],[-105.789,149.638],[-104.455,149.793],[-76.402,147.342],[-73.702,145.48],[-42.204,79.319],[-39.38,77.426],[111.127,70.599],[113.982,68.706],[145.666,0.962],[142.78,-3.755],[34.539,-7.137],[31.684,-11.916],[72.305,-93.966],[72.584,-94.711],[83.849,-145.852],[80.622,-149.855],[44.842,-149.855],[34.259,-144.642],[-43.477,-43.662],[-48.752,-27.929],[16.075,13.344],[53.282,12.599],[58.806,23.492],[54.431,30.226],[39.256,37.984],[-81.491,42.452],[-96.169,50.986],[-143.99,125.774],[-140.328,137.908],[-140.018,138.032]],"c":true},"ix":2},"nm":"Path 1","mn":"ADBE Vector Shape - Group","hd":false},{"ty":"fl","c":{"a":0,"k":[0.301960784314,0.635294117647,1,1],"ix":4},"o":{"a":0,"k":100,"ix":5},"r":1,"bm":0,"nm":"Fill 1","mn":"ADBE Vector Graphic - Fill","hd":false},{"ty":"tr","p":{"a":0,"k":[208.256,255.855],"ix":2},"a":{"a":0,"k":[0,0],"ix":1},"s":{"a":0,"k":[100,100],"ix":3},"r":{"a":0,"k":0,"ix":6},"o":{"a":0,"k":100,"ix":7},"sk":{"a":0,"k":0,"ix":4},"sa":{"a":0,"k":0,"ix":5},"nm":"Transform"}],"nm":"Group 2","np":2,"cix":2,"bm":0,"ix":2,"mn":"ADBE Vector Group","hd":false}],"ip":-10,"op":80,"st":-10,"bm":0},{"ddd":0,"ind":2,"ty":4,"nm":"TEXT__V Outlines","sr":1,"ks":{"o":{"a":1,"k":[{"i":{"x":[0.667],"y":[1]},"o":{"x":[0.333],"y":[0]},"t":5,"s":[0]},{"i":{"x":[0.833],"y":[1]},"o":{"x":[0.167],"y":[0]},"t":10,"s":[100]},{"i":{"x":[0.833],"y":[1]},"o":{"x":[0.167],"y":[0]},"t":40,"s":[100]},{"t":45,"s":[0]}],"ix":11},"r":{"a":0,"k":0,"ix":10},"p":{"a":1,"k":[{"i":{"x":0.667,"y":1},"o":{"x":0.668,"y":0},"t":0,"s":[434,-182,0],"to":[-39.5,68.333,0],"ti":[0,0,0]},{"i":{"x":0.667,"y":1},"o":{"x":1,"y":0},"t":10,"s":[197,228,0],"to":[0,0,0],"ti":[0,0,0]},{"i":{"x":0.667,"y":1},"o":{"x":0.167,"y":0},"t":16.25,"s":[217,237,0],"to":[0,0,0],"ti":[1.083,-1.667,0]},{"t":40,"s":[210.5,247,0]}],"ix":2},"a":{"a":0,"k":[256,256,0],"ix":1},"s":{"a":1,"k":[{"i":{"x":[0.667,0.667,0.667],"y":[1,1,1]},"o":{"x":[1,1,0.333],"y":[0,0,0]},"t":10,"s":[82.031,82.031,100]},{"i":{"x":[0.667,0.667,0.667],"y":[1,1,1]},"o":{"x":[0.167,0.167,0.167],"y":[0,0,0]},"t":16,"s":[50.781,50.781,100]},{"t":22,"s":[50.781,50.781,100]}],"ix":6}},"ao":0,"shapes":[{"ty":"gr","it":[{"ind":0,"ty":"sh","ix":1,"ks":{"a":0,"k":{"i":[[0,0],[0,0],[-0.621,-0.806],[-8.534,9.682],[-37.021,53.686],[5.493,0.217],[0,0],[3.352,-5.679],[0,0],[0,0],[1.645,5.523],[4.003,22.033],[3.165,0],[0,0],[0,0],[0,0],[-0.993,-4.376]],"o":[[0,0],[0.217,0.993],[2.234,2.886],[9.838,-11.141],[3.134,-4.531],[0,0],[-6.672,0],[0,0],[-0.279,0.404],[-4.624,5.555],[-2.452,-8.162],[-0.559,-3.134],[0,0],[0,0],[0,0],[-4.469,0],[0,0]],"v":[[-146.24,-101.538],[-88.674,153.61],[-87.402,156.34],[-70.708,154.852],[144.068,-153.299],[138.574,-164.224],[61.087,-164.534],[47.96,-157.521],[-41.227,-22.189],[-43.43,-19.241],[-51.902,-21.07],[-71.079,-108.428],[-77.814,-113.641],[-86.876,-113.113],[-90.971,-112.865],[-139.413,-110.072],[-146.208,-101.569]],"c":true},"ix":2},"nm":"Path 1","mn":"ADBE Vector Shape - Group","hd":false},{"ty":"fl","c":{"a":0,"k":[0.988235353956,0.988235353956,0.988235353956,1],"ix":4},"o":{"a":0,"k":100,"ix":5},"r":1,"bm":0,"nm":"Fill 1","mn":"ADBE Vector Graphic - Fill","hd":false},{"ty":"tr","p":{"a":0,"k":[235.385,258.534],"ix":2},"a":{"a":0,"k":[0,0],"ix":1},"s":{"a":0,"k":[100,100],"ix":3},"r":{"a":0,"k":0,"ix":6},"o":{"a":0,"k":100,"ix":7},"sk":{"a":0,"k":0,"ix":4},"sa":{"a":0,"k":0,"ix":5},"nm":"Transform"}],"nm":"Group 1","np":2,"cix":2,"bm":0,"ix":1,"mn":"ADBE Vector Group","hd":false},{"ty":"gr","it":[{"ind":0,"ty":"sh","ix":1,"ks":{"a":0,"k":{"i":[[3.755,-0.186],[0,0],[0,0],[0,0],[0,0],[0,0]],"o":[[0,0],[0,0],[0,0],[0,0],[0,0],[-1.862,-3.289]],"v":[[18.805,-69.419],[-53.872,-65.788],[-18.123,69.605],[47.138,61.134],[53.872,20.451],[27.991,-64.361]],"c":true},"ix":2},"nm":"Path 1","mn":"ADBE Vector Shape - Group","hd":false},{"ty":"fl","c":{"a":0,"k":[0.980392216701,0.305882352941,0.529411764706,1],"ix":4},"o":{"a":0,"k":100,"ix":5},"r":1,"bm":0,"nm":"Fill 1","mn":"ADBE Vector Graphic - Fill","hd":false},{"ty":"tr","p":{"a":0,"k":[180.97,212.512],"ix":2},"a":{"a":0,"k":[0,0],"ix":1},"s":{"a":0,"k":[100,100],"ix":3},"r":{"a":0,"k":0,"ix":6},"o":{"a":0,"k":100,"ix":7},"sk":{"a":0,"k":0,"ix":4},"sa":{"a":0,"k":0,"ix":5},"nm":"Transform"}],"nm":"Group 2","np":2,"cix":2,"bm":0,"ix":2,"mn":"ADBE Vector Group","hd":false},{"ty":"gr","it":[{"ind":0,"ty":"sh","ix":1,"ks":{"a":0,"k":{"i":[[0,0],[0,0],[-2.824,4.003],[0,0],[8.131,0],[0,0],[0,0],[0,0]],"o":[[0,0],[4.717,-1.366],[0,0],[4.686,-6.641],[0,0],[0,0],[0,0],[0,0]],"v":[[-135.41,162.346],[-82.22,147.078],[-70.583,138.792],[130.724,-146.085],[122.531,-161.911],[51.778,-162.377],[-135.41,141.306],[-135.41,162.377]],"c":true},"ix":2},"nm":"Path 1","mn":"ADBE Vector Shape - Group","hd":false},{"ty":"fl","c":{"a":0,"k":[0.980392216701,0.305882352941,0.529411764706,1],"ix":4},"o":{"a":0,"k":100,"ix":5},"r":1,"bm":0,"nm":"Fill 1","mn":"ADBE Vector Graphic - Fill","hd":false},{"ty":"tr","p":{"a":0,"k":[291.244,256.594],"ix":2},"a":{"a":0,"k":[0,0],"ix":1},"s":{"a":0,"k":[100,100],"ix":3},"r":{"a":0,"k":0,"ix":6},"o":{"a":0,"k":100,"ix":7},"sk":{"a":0,"k":0,"ix":4},"sa":{"a":0,"k":0,"ix":5},"nm":"Transform"}],"nm":"Group 3","np":2,"cix":2,"bm":0,"ix":3,"mn":"ADBE Vector Group","hd":false}],"ip":-10,"op":80,"st":-10,"bm":0},{"ddd":0,"ind":3,"ty":0,"nm":"Comp 1","refId":"comp_0","sr":1,"ks":{"o":{"a":1,"k":[{"i":{"x":[0.667],"y":[1]},"o":{"x":[0.333],"y":[0]},"t":11,"s":[0]},{"i":{"x":[0.833],"y":[1]},"o":{"x":[0.167],"y":[0]},"t":16,"s":[100]},{"i":{"x":[0.833],"y":[1]},"o":{"x":[0.167],"y":[0]},"t":22,"s":[100]},{"t":32.5,"s":[0]}],"ix":11},"r":{"a":0,"k":0,"ix":10},"p":{"a":0,"k":[256,256,0],"ix":2},"a":{"a":0,"k":[400,300,0],"ix":1},"s":{"a":0,"k":[133.333,133.333,100],"ix":6}},"ao":0,"w":800,"h":600,"ip":10,"op":181.191191191191,"st":-10,"bm":0}],"markers":[{"tm":10,"cm":"STAR","dr":0},{"tm":20,"cm":"SCALE_","dr":0},{"tm":32,"cm":"SLOW","dr":0}]}